{
    "sList": [
        {
            "chapterIndex": 0,
            "levelIndex": 0,
            "ruleInfoDict": {
                "m_keys": [
                    3,
                    4,
                    2,
                    1
                ],
                "m_values": [
                    {
                        "attributeList": [
                            4
                        ]
                    },
                    {
                        "attributeList": [
                            0
                        ]
                    },
                    {
                        "attributeList": [
                            1
                        ]
                    },
                    {
                        "attributeList": [
                            6
                        ]
                    }
                ]
            }
        }
    ]
}
